MANIFEST.in
README.rst
setup.py
tweet_archiver/__init__.py
tweet_archiver.egg-info/PKG-INFO
tweet_archiver.egg-info/SOURCES.txt
tweet_archiver.egg-info/dependency_links.txt
tweet_archiver.egg-info/entry_points.txt
tweet_archiver.egg-info/requires.txt
tweet_archiver.egg-info/top_level.txt
tweet_archiver.egg-info/zip-safe