Metadata-Version: 1.0
Name: tweet-archiver
Version: 0.2
Summary: Get full Tweet metadata given a list of status IDs.
Home-page: UNKNOWN
Author: Alex Muller
Author-email: alex@mullr.net
License: UNKNOWN
Platform: UNKNOWN
